src/__init__.py
src/mhaptk.py
mHapTk-1.0.dist-info/LICENSE.txt
mHapTk-1.0.dist-info/METADATA
mHapTk-1.0.dist-info/WHEEL
mHapTk-1.0.dist-info/entry_points.txt
mHapTk-1.0.dist-info/top_level.txt
mHapTk-1.0.dist-info/RECORD
